tencentcloud/__init__.py
tencentcloud/yunsou/__init__.py
tencentcloud/yunsou/v20180504/__init__.py
tencentcloud/yunsou/v20180504/errorcodes.py
tencentcloud/yunsou/v20180504/models.py
tencentcloud/yunsou/v20180504/yunsou_client.py
tencentcloud/yunsou/v20191115/__init__.py
tencentcloud/yunsou/v20191115/errorcodes.py
tencentcloud/yunsou/v20191115/models.py
tencentcloud/yunsou/v20191115/yunsou_client.py
tencentcloud_sdk_python_yunsou-3.0.1459.dist-info/METADATA
tencentcloud_sdk_python_yunsou-3.0.1459.dist-info/WHEEL
tencentcloud_sdk_python_yunsou-3.0.1459.dist-info/top_level.txt
tencentcloud_sdk_python_yunsou-3.0.1459.dist-info/RECORD
